{"8lmpvnv6svee-0vq8sbjw-490wamw9ddw-p9855egg0-9n2akdy3rm-cxxe8psn-fihietvrja2-8lmqo9uj-7v51k44b8o0-ns0b4shg1":{"data":{"name":"Acoustic charts, week #9 / 2023","tracks":[{"key":"8lmpvnv6svee","id":-1,"name":"Home <3","created":1676338386000,"modified":1676344394000,"user":{"key":"faked00f","name":"Doof","avatar":"https://api.audiotool.com/user/faked00f/avatar/256.jpg"},"template":false,"published":true,"snapshotUrl":"//at-cdn-s03.audiotool.com/2023/02/14/documents/8lmpvnv6svee/snapshot640x480-80fce558e79042b5ac3685acc00b0e8a-160.jpg","pksUrl":"//at-cdn-s03.audiotool.com/2023/02/14/documents/8lmpvnv6svee/ddfba199a43d434e912b73b5e36b051b.pks","coverUrl":"//at-cdn-s03.audiotool.com/2023/02/14/documents/8lmpvnv6svee/0/cover128x128-bd3fbbb53a9e46b7b4bc524336472cbd.jpg","collaborators":[{"key":"faked00f","name":"Doof","avatar":"https://api.audiotool.com/user/faked00f/avatar/256.jpg"}],"bpm":70,"genreKey":"acoustic","genreName":"Acoustic","duration":120000.72562358277,"isNextTrack":true,"joinPolicy":0,"license":2},{"key":"0vq8sbjw","id":-1,"name":"PO9T REMIX COMP 7","created":1674669652000,"modified":1674669652000,"user":{"key":"lowkei","name":"LATE2THEPRTY.","avatar":"https://api.audiotool.com/user/lowkei/avatar/256.jpg"},"template":false,"published":true,"snapshotUrl":"//at-cdn-s03.audiotool.com/2023/01/25/documents/0vq8sbjw/snapshot640x480-4f511e7ac73a487c9e60b8b55e03313c-160.jpg","pksUrl":"//at-cdn-s03.audiotool.com/2023/01/25/documents/0vq8sbjw/691212a8ad484697bf83d2060673a98e.pks","coverUrl":"//at-cdn-s03.audiotool.com/2023/01/22/documents/0vq8sbjw/0/cover128x128-32dae395249548609ff7e2734dc747cd.jpg","collaborators":[{"key":"lowkei","name":"LATE2THEPRTY.","avatar":"https://api.audiotool.com/user/lowkei/avatar/256.jpg"},{"key":"bubblicious","name":"Zack","avatar":"https://api.audiotool.com/user/bubblicious/avatar/256.jpg"}],"bpm":138,"genreKey":"acoustic","genreName":"Acoustic","duration":114056.4172335601,"isNextTrack":true,"joinPolicy":0,"license":2},{"key":"490wamw9ddw","id":-1,"name":"PO9T REMIX COMP 7","created":1673990884000,"modified":1673990884000,"user":{"key":"anotherevolution","name":"po9t","avatar":"https://api.audiotool.com/user/anotherevolution/avatar/256.jpg"},"template":false,"published":true,"snapshotUrl":"//at-cdn-s03.audiotool.com/2023/01/17/documents/490wamw9ddw/snapshot640x480-e470c65710dd4c06a7b7f1839555af47-160.jpg","pksUrl":"//at-cdn-s03.audiotool.com/2023/01/17/documents/490wamw9ddw/cfb63550ed6d4432b8d52e6c9dfa8b26.pks","coverUrl":"//at-cdn-s03.audiotool.com/2023/01/17/documents/490wamw9ddw/0/cover128x128-924ce4b4c5ac4576908c9074219a2e4e.jpg","collaborators":[{"key":"anotherevolution","name":"po9t","avatar":"https://api.audiotool.com/user/anotherevolution/avatar/256.jpg"}],"bpm":146,"genreKey":"acoustic","genreName":"Acoustic","duration":26331.428571428572,"isNextTrack":true,"joinPolicy":0,"license":4},{"key":"p9855egg0","id":-1,"name":"p9855egg0 / po9t","created":1674998849000,"modified":1675628054000,"user":{"key":"kepz","name":"Kepz","avatar":"https://api.audiotool.com/user/kepz/avatar/256.jpg"},"template":false,"published":true,"snapshotUrl":"//at-cdn-s03.audiotool.com/2023/02/05/documents/p9855egg0/snapshot640x480-b434f26fc60d4b059da41131b7c5734a-160.jpg","pksUrl":"//at-cdn-s03.audiotool.com/2023/02/05/documents/p9855egg0/9c10f47eca3f4d5185cd546b3681428b.pks","coverUrl":"//at-cdn-s03.audiotool.com/2023/01/29/documents/p9855egg0/0/cover128x128-a0bdf10999ef4ad4a10ac498688cac5e.jpg","collaborators":[{"key":"kepz","name":"Kepz","avatar":"https://api.audiotool.com/user/kepz/avatar/256.jpg"}],"bpm":146,"genreKey":"acoustic","genreName":"Acoustic","duration":217013.69614512473,"isNextTrack":true,"joinPolicy":0,"license":2},{"key":"9n2akdy3rm","id":-1,"name":"rymdskepp","created":1653270410000,"modified":1673586066000,"user":{"key":"balisthey","name":"youdontknowme","avatar":"https://api.audiotool.com/user/balisthey/avatar/256.jpg"},"template":false,"published":true,"snapshotUrl":"//at-cdn-s03.audiotool.com/2023/01/13/documents/9n2akdy3rm/snapshot640x480-8afbfa972a174960b559fe9759662111-160.jpg","pksUrl":"//at-cdn-s03.audiotool.com/2023/01/13/documents/9n2akdy3rm/b7787fbb7fb84c85af98db6ebf398922.pks","coverUrl":"//at-cdn-s03.audiotool.com/2022/05/23/documents/9n2akdy3rm/2/cover128x128-b9d38d82682145548b31d94375638762.jpg","collaborators":[{"key":"balisthey","name":"youdontknowme","avatar":"https://api.audiotool.com/user/balisthey/avatar/256.jpg"}],"bpm":138,"genreKey":"acoustic","genreName":"Acoustic","duration":118282.44897959183,"isNextTrack":true,"joinPolicy":0,"license":2},{"key":"cxxe8psn","id":-1,"name":"Piano Patch [v2]","created":1652254666000,"modified":1652257808000,"user":{"key":"deepwave","name":"sea foam and the wind","avatar":"https://api.audiotool.com/user/deepwave/avatar/256.jpg"},"template":false,"published":true,"snapshotUrl":"//at-cdn-s03.audiotool.com/2022/05/11/documents/cxxe8psn/snapshot640x480-ecf44926c64247bf9423cbabb1155cef-160.jpg","pksUrl":"//at-cdn-s03.audiotool.com/2022/05/11/documents/cxxe8psn/170d65f8c9bb40b3b4c91eb2e81aa3ef.pks","coverUrl":"//at-cdn-s03.audiotool.com/2022/05/03/documents/cxxe8psn/0/cover128x128-91d51237546a4a6eb0388189f1efc45e.jpg","collaborators":[{"key":"deepwave","name":"sea foam and the wind","avatar":"https://api.audiotool.com/user/deepwave/avatar/256.jpg"},{"key":"nick123456","name":"Vulkron","avatar":"https://api.audiotool.com/user/nick123456/avatar/256.jpg"}],"bpm":67,"genreKey":"acoustic","genreName":"Acoustic","duration":214970.34013605444,"isNextTrack":true,"joinPolicy":0,"license":2},{"key":"fihietvrja2","id":-1,"name":"1hr remis","created":1674178252000,"modified":1674178252000,"user":{"key":"sunder","name":"Sunder","avatar":"https://api.audiotool.com/user/sunder/avatar/256.jpg"},"template":false,"published":true,"snapshotUrl":"//at-cdn-s03.audiotool.com/2023/01/20/documents/fihietvrja2/snapshot640x480-94aa0aa7f1d14c0cbd8c6339515afd47-160.jpg","pksUrl":"//at-cdn-s03.audiotool.com/2023/01/20/documents/fihietvrja2/7e025b21b5354d2797eb16ea7f38b5dc.pks","coverUrl":"//at-cdn-s03.audiotool.com/2023/01/20/documents/fihietvrja2/0/cover128x128-fb5fe42b309544bc965cb50744a82c20.jpg","collaborators":[{"key":"sunder","name":"Sunder","avatar":"https://api.audiotool.com/user/sunder/avatar/256.jpg"}],"bpm":146,"genreKey":"acoustic","genreName":"Acoustic","duration":83870.4761904762,"isNextTrack":true,"joinPolicy":0,"license":2},{"key":"8lmqo9uj","id":-1,"name":"PO9T REMIX COMP 7","created":1676100629000,"modified":1676100629000,"user":{"key":"mdevesh","name":"SYNRGY","avatar":"https://api.audiotool.com/user/mdevesh/avatar/256.jpg"},"template":false,"published":true,"snapshotUrl":"//at-cdn-s03.audiotool.com/2023/02/11/documents/8lmqo9uj/snapshot640x480-43cfe73210b244c19efe528cc5a0c54e-160.jpg","pksUrl":"//at-cdn-s03.audiotool.com/2023/02/11/documents/8lmqo9uj/8ab3b4ff5bef483b9a5ded79dfd04140.pks","coverUrl":"//at-cdn-s03.audiotool.com/2023/02/07/documents/8lmqo9uj/0/cover128x128-99b00a6603f54017939bebd9c853b217.jpg","collaborators":[{"key":"mdevesh","name":"SYNRGY","avatar":"https://api.audiotool.com/user/mdevesh/avatar/256.jpg"}],"bpm":128,"genreKey":"acoustic","genreName":"Acoustic","duration":103143.03854875284,"isNextTrack":true,"joinPolicy":0,"license":2},{"key":"7v51k44b8o0","id":-1,"name":"PO9T plug","created":1673998262000,"modified":1674002649000,"user":{"key":"tjthjjg","name":"guyy","avatar":"https://api.audiotool.com/user/tjthjjg/avatar/256.jpg"},"template":false,"published":true,"snapshotUrl":"//at-cdn-s03.audiotool.com/2023/01/18/documents/7v51k44b8o0/snapshot640x480-645bd2adde5e46efa696f862d13a6810-160.jpg","pksUrl":"//at-cdn-s03.audiotool.com/2023/01/18/documents/7v51k44b8o0/e086c418185444339f39b846b30de918.pks","coverUrl":"//at-cdn-s03.audiotool.com/2023/01/17/documents/490wamw9ddw/0/cover128x128-924ce4b4c5ac4576908c9074219a2e4e.jpg","collaborators":[{"key":"tjthjjg","name":"guyy","avatar":"https://api.audiotool.com/user/tjthjjg/avatar/256.jpg"}],"bpm":138,"genreKey":"acoustic","genreName":"Acoustic","duration":55681.45124716553,"isNextTrack":true,"joinPolicy":0,"license":2},{"key":"ns0b4shg1","id":-1,"name":"dimming rays","created":1643607254000,"modified":1643636110000,"user":{"key":"kepz","name":"Kepz","avatar":"https://api.audiotool.com/user/kepz/avatar/256.jpg"},"template":false,"published":true,"snapshotUrl":"//at-cdn-s03.audiotool.com/2022/01/31/documents/ns0b4shg1/snapshot640x480-f6ae72fee1b84b98bc02cfaa88263a3b-160.jpg","pksUrl":"//at-cdn-s03.audiotool.com/2022/01/31/documents/ns0b4shg1/abf94273c3904c56b4acaf4bf834c17e.pks","collaborators":[],"bpm":132,"genreKey":"acoustic","genreName":"Acoustic","duration":207307.75510204083,"isNextTrack":true,"joinPolicy":0,"license":4}]},"runtime":1677388049990},"8lmpvnv6svee-490wamw9ddw-0vq8sbjw-8lmqo9uj-tsu3gyw5mcxq-7v51k44b8o0-ns0b4shg1-p9855egg0-cxxe8psn-aohjnyo5a06":{"data":{"name":"Acoustic charts, week #10 / 2023","tracks":[{"key":"8lmpvnv6svee","id":-1,"name":"Home <3","created":1676338386000,"modified":1676344394000,"user":{"key":"faked00f","name":"Doof","avatar":"https://api.audiotool.com/user/faked00f/avatar/256.jpg"},"template":false,"published":true,"snapshotUrl":"//at-cdn-s03.audiotool.com/2023/02/14/documents/8lmpvnv6svee/snapshot640x480-80fce558e79042b5ac3685acc00b0e8a-160.jpg","pksUrl":"//at-cdn-s03.audiotool.com/2023/02/14/documents/8lmpvnv6svee/ddfba199a43d434e912b73b5e36b051b.pks","coverUrl":"//at-cdn-s03.audiotool.com/2023/02/14/documents/8lmpvnv6svee/0/cover128x128-bd3fbbb53a9e46b7b4bc524336472cbd.jpg","collaborators":[{"key":"faked00f","name":"Doof","avatar":"https://api.audiotool.com/user/faked00f/avatar/256.jpg"}],"bpm":70,"genreKey":"acoustic","genreName":"Acoustic","duration":120000.72562358277,"isNextTrack":true,"joinPolicy":0,"license":2},{"key":"490wamw9ddw","id":-1,"name":"PO9T REMIX COMP 7","created":1673990884000,"modified":1673990884000,"user":{"key":"anotherevolution","name":"po9t","avatar":"https://api.audiotool.com/user/anotherevolution/avatar/256.jpg"},"template":false,"published":true,"snapshotUrl":"//at-cdn-s03.audiotool.com/2023/01/17/documents/490wamw9ddw/snapshot640x480-e470c65710dd4c06a7b7f1839555af47-160.jpg","pksUrl":"//at-cdn-s03.audiotool.com/2023/01/17/documents/490wamw9ddw/cfb63550ed6d4432b8d52e6c9dfa8b26.pks","coverUrl":"//at-cdn-s03.audiotool.com/2023/01/17/documents/490wamw9ddw/0/cover128x128-924ce4b4c5ac4576908c9074219a2e4e.jpg","collaborators":[{"key":"anotherevolution","name":"po9t","avatar":"https://api.audiotool.com/user/anotherevolution/avatar/256.jpg"}],"bpm":146,"genreKey":"acoustic","genreName":"Acoustic","duration":26331.428571428572,"isNextTrack":true,"joinPolicy":0,"license":4},{"key":"0vq8sbjw","id":-1,"name":"PO9T REMIX COMP 7","created":1674669652000,"modified":1674669652000,"user":{"key":"lowkei","name":"LATE2THEPRTY.","avatar":"https://api.audiotool.com/user/lowkei/avatar/256.jpg"},"template":false,"published":true,"snapshotUrl":"//at-cdn-s03.audiotool.com/2023/01/25/documents/0vq8sbjw/snapshot640x480-4f511e7ac73a487c9e60b8b55e03313c-160.jpg","pksUrl":"//at-cdn-s03.audiotool.com/2023/01/25/documents/0vq8sbjw/691212a8ad484697bf83d2060673a98e.pks","coverUrl":"//at-cdn-s03.audiotool.com/2023/01/22/documents/0vq8sbjw/0/cover128x128-32dae395249548609ff7e2734dc747cd.jpg","collaborators":[{"key":"lowkei","name":"LATE2THEPRTY.","avatar":"https://api.audiotool.com/user/lowkei/avatar/256.jpg"},{"key":"bubblicious","name":"Zack","avatar":"https://api.audiotool.com/user/bubblicious/avatar/256.jpg"}],"bpm":138,"genreKey":"acoustic","genreName":"Acoustic","duration":114056.4172335601,"isNextTrack":true,"joinPolicy":0,"license":2},{"key":"8lmqo9uj","id":-1,"name":"PO9T REMIX COMP 7","created":1676100629000,"modified":1676100629000,"user":{"key":"mdevesh","name":"SYNRGY","avatar":"https://api.audiotool.com/user/mdevesh/avatar/256.jpg"},"template":false,"published":true,"snapshotUrl":"//at-cdn-s03.audiotool.com/2023/02/11/documents/8lmqo9uj/snapshot640x480-43cfe73210b244c19efe528cc5a0c54e-160.jpg","pksUrl":"//at-cdn-s03.audiotool.com/2023/02/11/documents/8lmqo9uj/8ab3b4ff5bef483b9a5ded79dfd04140.pks","coverUrl":"//at-cdn-s03.audiotool.com/2023/02/07/documents/8lmqo9uj/0/cover128x128-99b00a6603f54017939bebd9c853b217.jpg","collaborators":[{"key":"mdevesh","name":"SYNRGY","avatar":"https://api.audiotool.com/user/mdevesh/avatar/256.jpg"}],"bpm":128,"genreKey":"acoustic","genreName":"Acoustic","duration":103143.03854875284,"isNextTrack":true,"joinPolicy":0,"license":2},{"key":"tsu3gyw5mcxq","id":-1,"name":"PO9T REMIX COMP 7 (Lr ENtry)","created":1677673685000,"modified":1677673685000,"user":{"key":"lrider","name":"LRider","avatar":"https://api.audiotool.com/user/lrider/avatar/256.jpg"},"template":false,"published":true,"snapshotUrl":"//at-cdn-s03.audiotool.com/2023/03/01/documents/tsu3gyw5mcxq/snapshot640x480-5bc4004e68d94416a3cd9905622f5bd5-160.jpg","pksUrl":"//at-cdn-s03.audiotool.com/2023/03/01/documents/tsu3gyw5mcxq/de451e078fee449bb4b35986b35e452b.pks","coverUrl":"//at-cdn-s03.audiotool.com/2023/02/28/documents/tsu3gyw5mcxq/0/cover128x128-4ad80b489ccb427d8ed705e963fabb11.jpg","collaborators":[{"key":"lrider","name":"LRider","avatar":"https://api.audiotool.com/user/lrider/avatar/256.jpg"}],"bpm":146,"genreKey":"acoustic","genreName":"Acoustic","duration":210419.2290249433,"isNextTrack":true,"joinPolicy":0,"license":2},{"key":"7v51k44b8o0","id":-1,"name":"PO9T plug","created":1673998262000,"modified":1674002649000,"user":{"key":"tjthjjg","name":"guyy","avatar":"https://api.audiotool.com/user/tjthjjg/avatar/256.jpg"},"template":false,"published":true,"snapshotUrl":"//at-cdn-s03.audiotool.com/2023/01/18/documents/7v51k44b8o0/snapshot640x480-645bd2adde5e46efa696f862d13a6810-160.jpg","pksUrl":"//at-cdn-s03.audiotool.com/2023/01/18/documents/7v51k44b8o0/e086c418185444339f39b846b30de918.pks","coverUrl":"//at-cdn-s03.audiotool.com/2023/01/17/documents/490wamw9ddw/0/cover128x128-924ce4b4c5ac4576908c9074219a2e4e.jpg","collaborators":[{"key":"tjthjjg","name":"guyy","avatar":"https://api.audiotool.com/user/tjthjjg/avatar/256.jpg"}],"bpm":138,"genreKey":"acoustic","genreName":"Acoustic","duration":55681.45124716553,"isNextTrack":true,"joinPolicy":0,"license":2},{"key":"ns0b4shg1","id":-1,"name":"dimming rays","created":1643607254000,"modified":1643636110000,"user":{"key":"kepz","name":"Kepz","avatar":"https://api.audiotool.com/user/kepz/avatar/256.jpg"},"template":false,"published":true,"snapshotUrl":"//at-cdn-s03.audiotool.com/2022/01/31/documents/ns0b4shg1/snapshot640x480-f6ae72fee1b84b98bc02cfaa88263a3b-160.jpg","pksUrl":"//at-cdn-s03.audiotool.com/2022/01/31/documents/ns0b4shg1/abf94273c3904c56b4acaf4bf834c17e.pks","collaborators":[],"bpm":132,"genreKey":"acoustic","genreName":"Acoustic","duration":207307.75510204083,"isNextTrack":true,"joinPolicy":0,"license":4},{"key":"p9855egg0","id":-1,"name":"p9855egg0 / po9t","created":1674998849000,"modified":1675628054000,"user":{"key":"kepz","name":"Kepz","avatar":"https://api.audiotool.com/user/kepz/avatar/256.jpg"},"template":false,"published":true,"snapshotUrl":"//at-cdn-s03.audiotool.com/2023/02/05/documents/p9855egg0/snapshot640x480-b434f26fc60d4b059da41131b7c5734a-160.jpg","pksUrl":"//at-cdn-s03.audiotool.com/2023/02/05/documents/p9855egg0/9c10f47eca3f4d5185cd546b3681428b.pks","coverUrl":"//at-cdn-s03.audiotool.com/2023/01/29/documents/p9855egg0/0/cover128x128-a0bdf10999ef4ad4a10ac498688cac5e.jpg","collaborators":[{"key":"kepz","name":"Kepz","avatar":"https://api.audiotool.com/user/kepz/avatar/256.jpg"}],"bpm":146,"genreKey":"acoustic","genreName":"Acoustic","duration":217013.69614512473,"isNextTrack":true,"joinPolicy":0,"license":2},{"key":"cxxe8psn","id":-1,"name":"Piano Patch [v2]","created":1652254666000,"modified":1652257808000,"user":{"key":"deepwave","name":"sea foam and the wind","avatar":"https://api.audiotool.com/user/deepwave/avatar/256.jpg"},"template":false,"published":true,"snapshotUrl":"//at-cdn-s03.audiotool.com/2022/05/11/documents/cxxe8psn/snapshot640x480-ecf44926c64247bf9423cbabb1155cef-160.jpg","pksUrl":"//at-cdn-s03.audiotool.com/2022/05/11/documents/cxxe8psn/170d65f8c9bb40b3b4c91eb2e81aa3ef.pks","coverUrl":"//at-cdn-s03.audiotool.com/2022/05/03/documents/cxxe8psn/0/cover128x128-91d51237546a4a6eb0388189f1efc45e.jpg","collaborators":[{"key":"deepwave","name":"sea foam and the wind","avatar":"https://api.audiotool.com/user/deepwave/avatar/256.jpg"},{"key":"nick123456","name":"Vulkron","avatar":"https://api.audiotool.com/user/nick123456/avatar/256.jpg"}],"bpm":67,"genreKey":"acoustic","genreName":"Acoustic","duration":214970.34013605444,"isNextTrack":true,"joinPolicy":0,"license":2},{"key":"aohjnyo5a06","id":-1,"name":"Eric Eric","created":1676381926000,"modified":1676381926000,"user":{"key":"ebenezerstudios","name":"EbenezerStudios","avatar":"https://api.audiotool.com/user/ebenezerstudios/avatar/256.jpg"},"template":false,"published":true,"snapshotUrl":"//at-cdn-s03.audiotool.com/2023/02/14/documents/aohjnyo5a06/snapshot640x480-640903241b6a439880952f7b29701707-160.jpg","pksUrl":"//at-cdn-s03.audiotool.com/2023/02/14/documents/aohjnyo5a06/d107e378567449ccbd31c98ec5d23daf.pks","coverUrl":"//at-cdn-s03.audiotool.com/2023/02/13/documents/aohjnyo5a06/0/cover128x128-f767e63fa9bc43978f281e4c290b54ed.jpg","collaborators":[{"key":"ebenezerstudios","name":"EbenezerStudios","avatar":"https://api.audiotool.com/user/ebenezerstudios/avatar/256.jpg"}],"bpm":120,"genreKey":"acoustic","genreName":"Acoustic","duration":81037.641723356,"isNextTrack":true,"joinPolicy":0,"license":2}]},"runtime":1677977168525},"490wamw9ddw-tsu3gyw5mcxq-8lmpvnv6svee-0vq8sbjw-7v51k44b8o0-8lmqo9uj-cxxe8psn-aohjnyo5a06-3164v0i7-wm6kblrg063x":{"data":{"name":"Acoustic charts, week #11 / 2023","tracks":[{"key":"490wamw9ddw","id":-1,"name":"PO9T REMIX COMP 7","created":1673990884000,"modified":1673990884000,"user":{"key":"anotherevolution","name":"po9t","avatar":"https://api.audiotool.com/user/anotherevolution/avatar/256.jpg"},"template":false,"published":true,"snapshotUrl":"//at-cdn-s03.audiotool.com/2023/01/17/documents/490wamw9ddw/snapshot640x480-e470c65710dd4c06a7b7f1839555af47-160.jpg","pksUrl":"//at-cdn-s03.audiotool.com/2023/01/17/documents/490wamw9ddw/cfb63550ed6d4432b8d52e6c9dfa8b26.pks","coverUrl":"//at-cdn-s03.audiotool.com/2023/01/17/documents/490wamw9ddw/0/cover128x128-924ce4b4c5ac4576908c9074219a2e4e.jpg","collaborators":[{"key":"anotherevolution","name":"po9t","avatar":"https://api.audiotool.com/user/anotherevolution/avatar/256.jpg"}],"bpm":146,"genreKey":"acoustic","genreName":"Acoustic","duration":26331.428571428572,"isNextTrack":true,"joinPolicy":0,"license":4},{"key":"tsu3gyw5mcxq","id":-1,"name":"PO9T REMIX COMP 7 (Lr ENtry)","created":1677673685000,"modified":1677673685000,"user":{"key":"lrider","name":"LRider","avatar":"https://api.audiotool.com/user/lrider/avatar/256.jpg"},"template":false,"published":true,"snapshotUrl":"//at-cdn-s03.audiotool.com/2023/03/01/documents/tsu3gyw5mcxq/snapshot640x480-5bc4004e68d94416a3cd9905622f5bd5-160.jpg","pksUrl":"//at-cdn-s03.audiotool.com/2023/03/01/documents/tsu3gyw5mcxq/de451e078fee449bb4b35986b35e452b.pks","coverUrl":"//at-cdn-s03.audiotool.com/2023/02/28/documents/tsu3gyw5mcxq/0/cover128x128-4ad80b489ccb427d8ed705e963fabb11.jpg","collaborators":[{"key":"lrider","name":"LRider","avatar":"https://api.audiotool.com/user/lrider/avatar/256.jpg"}],"bpm":146,"genreKey":"acoustic","genreName":"Acoustic","duration":210419.2290249433,"isNextTrack":true,"joinPolicy":0,"license":2},{"key":"8lmpvnv6svee","id":-1,"name":"Home <3","created":1676338386000,"modified":1676344394000,"user":{"key":"faked00f","name":"Doof","avatar":"https://api.audiotool.com/user/faked00f/avatar/256.jpg"},"template":false,"published":true,"snapshotUrl":"//at-cdn-s03.audiotool.com/2023/02/14/documents/8lmpvnv6svee/snapshot640x480-80fce558e79042b5ac3685acc00b0e8a-160.jpg","pksUrl":"//at-cdn-s03.audiotool.com/2023/02/14/documents/8lmpvnv6svee/ddfba199a43d434e912b73b5e36b051b.pks","coverUrl":"//at-cdn-s03.audiotool.com/2023/02/14/documents/8lmpvnv6svee/0/cover128x128-bd3fbbb53a9e46b7b4bc524336472cbd.jpg","collaborators":[{"key":"faked00f","name":"Doof","avatar":"https://api.audiotool.com/user/faked00f/avatar/256.jpg"}],"bpm":70,"genreKey":"acoustic","genreName":"Acoustic","duration":120000.72562358277,"isNextTrack":true,"joinPolicy":0,"license":2},{"key":"0vq8sbjw","id":-1,"name":"PO9T REMIX COMP 7","created":1674669652000,"modified":1674669652000,"user":{"key":"lowkei","name":"LATE2THEPRTY.","avatar":"https://api.audiotool.com/user/lowkei/avatar/256.jpg"},"template":false,"published":true,"snapshotUrl":"//at-cdn-s03.audiotool.com/2023/01/25/documents/0vq8sbjw/snapshot640x480-4f511e7ac73a487c9e60b8b55e03313c-160.jpg","pksUrl":"//at-cdn-s03.audiotool.com/2023/01/25/documents/0vq8sbjw/691212a8ad484697bf83d2060673a98e.pks","coverUrl":"//at-cdn-s03.audiotool.com/2023/01/22/documents/0vq8sbjw/0/cover128x128-32dae395249548609ff7e2734dc747cd.jpg","collaborators":[{"key":"lowkei","name":"LATE2THEPRTY.","avatar":"https://api.audiotool.com/user/lowkei/avatar/256.jpg"},{"key":"bubblicious","name":"Zack","avatar":"https://api.audiotool.com/user/bubblicious/avatar/256.jpg"}],"bpm":138,"genreKey":"acoustic","genreName":"Acoustic","duration":114056.4172335601,"isNextTrack":true,"joinPolicy":0,"license":2},{"key":"7v51k44b8o0","id":-1,"name":"PO9T plug","created":1673998262000,"modified":1674002649000,"user":{"key":"tjthjjg","name":"guyy","avatar":"https://api.audiotool.com/user/tjthjjg/avatar/256.jpg"},"template":false,"published":true,"snapshotUrl":"//at-cdn-s03.audiotool.com/2023/01/18/documents/7v51k44b8o0/snapshot640x480-645bd2adde5e46efa696f862d13a6810-160.jpg","pksUrl":"//at-cdn-s03.audiotool.com/2023/01/18/documents/7v51k44b8o0/e086c418185444339f39b846b30de918.pks","coverUrl":"//at-cdn-s03.audiotool.com/2023/01/17/documents/490wamw9ddw/0/cover128x128-924ce4b4c5ac4576908c9074219a2e4e.jpg","collaborators":[{"key":"tjthjjg","name":"guyy","avatar":"https://api.audiotool.com/user/tjthjjg/avatar/256.jpg"}],"bpm":138,"genreKey":"acoustic","genreName":"Acoustic","duration":55681.45124716553,"isNextTrack":true,"joinPolicy":0,"license":2},{"key":"8lmqo9uj","id":-1,"name":"PO9T REMIX COMP 7","created":1676100629000,"modified":1676100629000,"user":{"key":"mdevesh","name":"SYNRGY","avatar":"https://api.audiotool.com/user/mdevesh/avatar/256.jpg"},"template":false,"published":true,"snapshotUrl":"//at-cdn-s03.audiotool.com/2023/02/11/documents/8lmqo9uj/snapshot640x480-43cfe73210b244c19efe528cc5a0c54e-160.jpg","pksUrl":"//at-cdn-s03.audiotool.com/2023/02/11/documents/8lmqo9uj/8ab3b4ff5bef483b9a5ded79dfd04140.pks","coverUrl":"//at-cdn-s03.audiotool.com/2023/02/07/documents/8lmqo9uj/0/cover128x128-99b00a6603f54017939bebd9c853b217.jpg","collaborators":[{"key":"mdevesh","name":"SYNRGY","avatar":"https://api.audiotool.com/user/mdevesh/avatar/256.jpg"}],"bpm":128,"genreKey":"acoustic","genreName":"Acoustic","duration":103143.03854875284,"isNextTrack":true,"joinPolicy":0,"license":2},{"key":"cxxe8psn","id":-1,"name":"Piano Patch [v2]","created":1652254666000,"modified":1652257808000,"user":{"key":"deepwave","name":"sea foam and the wind","avatar":"https://api.audiotool.com/user/deepwave/avatar/256.jpg"},"template":false,"published":true,"snapshotUrl":"//at-cdn-s03.audiotool.com/2022/05/11/documents/cxxe8psn/snapshot640x480-ecf44926c64247bf9423cbabb1155cef-160.jpg","pksUrl":"//at-cdn-s03.audiotool.com/2022/05/11/documents/cxxe8psn/170d65f8c9bb40b3b4c91eb2e81aa3ef.pks","coverUrl":"//at-cdn-s03.audiotool.com/2022/05/03/documents/cxxe8psn/0/cover128x128-91d51237546a4a6eb0388189f1efc45e.jpg","collaborators":[{"key":"deepwave","name":"sea foam and the wind","avatar":"https://api.audiotool.com/user/deepwave/avatar/256.jpg"},{"key":"nick123456","name":"Vulkron","avatar":"https://api.audiotool.com/user/nick123456/avatar/256.jpg"}],"bpm":67,"genreKey":"acoustic","genreName":"Acoustic","duration":214970.34013605444,"isNextTrack":true,"joinPolicy":0,"license":2},{"key":"aohjnyo5a06","id":-1,"name":"Eric Eric","created":1676381926000,"modified":1676381926000,"user":{"key":"ebenezerstudios","name":"EbenezerStudios","avatar":"https://api.audiotool.com/user/ebenezerstudios/avatar/256.jpg"},"template":false,"published":true,"snapshotUrl":"//at-cdn-s03.audiotool.com/2023/02/14/documents/aohjnyo5a06/snapshot640x480-640903241b6a439880952f7b29701707-160.jpg","pksUrl":"//at-cdn-s03.audiotool.com/2023/02/14/documents/aohjnyo5a06/d107e378567449ccbd31c98ec5d23daf.pks","coverUrl":"//at-cdn-s03.audiotool.com/2023/02/13/documents/aohjnyo5a06/0/cover128x128-f767e63fa9bc43978f281e4c290b54ed.jpg","collaborators":[{"key":"ebenezerstudios","name":"EbenezerStudios","avatar":"https://api.audiotool.com/user/ebenezerstudios/avatar/256.jpg"}],"bpm":120,"genreKey":"acoustic","genreName":"Acoustic","duration":81037.641723356,"isNextTrack":true,"joinPolicy":0,"license":2},{"key":"3164v0i7","id":-1,"name":"jam266","created":1677930175000,"modified":1678269989000,"user":{"key":"smirnusha_gmail_com","name":"Duston Mixers","avatar":"https://api.audiotool.com/user/smirnusha_gmail_com/avatar/256.jpg"},"template":false,"published":true,"snapshotUrl":"//at-cdn-s03.audiotool.com/2023/03/08/documents/3164v0i7/snapshot640x480-cdcdb1e3cd7d49ed93272d2ac02000ac-160.jpg","pksUrl":"//at-cdn-s03.audiotool.com/2023/03/08/documents/3164v0i7/9b47b0b9a1a54dd5840cdb32cc06671d.pks","collaborators":[{"key":"smirnusha_gmail_com","name":"Duston Mixers","avatar":"https://api.audiotool.com/user/smirnusha_gmail_com/avatar/256.jpg"}],"bpm":161,"genreKey":"acoustic","genreName":"Acoustic","duration":251564.98866213154,"isNextTrack":true,"joinPolicy":0,"license":2},{"key":"wm6kblrg063x","id":-1,"name":"jam255","created":1676810508000,"modified":1677244153000,"user":{"key":"smirnusha_gmail_com","name":"Duston Mixers","avatar":"https://api.audiotool.com/user/smirnusha_gmail_com/avatar/256.jpg"},"template":false,"published":true,"snapshotUrl":"//at-cdn-s03.audiotool.com/2023/02/24/documents/wm6kblrg063x/snapshot640x480-60f93f140353481cae6e093c8365192d-160.jpg","pksUrl":"//at-cdn-s03.audiotool.com/2023/02/24/documents/wm6kblrg063x/7924bc06cf9e42bd9cb95d0fe88949cf.pks","collaborators":[{"key":"smirnusha_gmail_com","name":"Duston Mixers","avatar":"https://api.audiotool.com/user/smirnusha_gmail_com/avatar/256.jpg"}],"bpm":103,"genreKey":"acoustic","genreName":"Acoustic","duration":207400.63492063494,"isNextTrack":true,"joinPolicy":0,"license":2}]},"runtime":1678581728506}}